hhnk_research_tools/__init__.py
hhnk_research_tools/dataframe_functions.py
hhnk_research_tools/general_functions.py
hhnk_research_tools/processes.py
hhnk_research_tools/raster_functions.py
hhnk_research_tools/sql_functions.py
hhnk_research_tools/variables.py
hhnk_research_tools/folder_file_classes/__init__.py
hhnk_research_tools/folder_file_classes/file_class.py
hhnk_research_tools/folder_file_classes/folder_file_classes.py
hhnk_research_tools/folder_file_classes/sqlite_class.py
hhnk_research_tools/folder_file_classes/threedi_schematisation.py
hhnk_research_tools/gis/__init__.py
hhnk_research_tools/gis/raster.py
hhnk_research_tools/gis/raster_calculator.py
hhnk_research_tools/gis/vector.py
hhnk_research_tools/threedi/__init__.py
hhnk_research_tools/threedi/call_api.py
hhnk_research_tools/threedi/construct_rain_scenario.py
hhnk_research_tools/threedi/construct_rain_scenario_dataframe.py
hhnk_research_tools/threedi/geometry_functions.py
hhnk_research_tools/threedi/grid.py
hhnk_research_tools/threedi/gridedit.py
hhnk_research_tools/threedi/read_api_file.py
hhnk_research_tools/threedi/threediresult_loader.py
hhnk_research_tools/threedi/variables/__init__.py
hhnk_research_tools/threedi/variables/gridadmin.py
hhnk_research_tools/threedi/variables/rain_dataframe.py
hhnk_research_tools/threedi/variables/results_mapping.py
hhnk_research_tools/threedi/variables/variables_container.py
hhnk_research_tools/waterschadeschatter/__init__.py
hhnk_research_tools/waterschadeschatter/wss_calculations.py
hhnk_research_tools/waterschadeschatter/wss_loading.py
hhnk_research_tools/waterschadeschatter/wss_main.py
hhnk_research_tools/waterschadeschatter/resources/__init__.py
hhnk_research_tools/waterschadeschatter/resources/cfg_hhnk_2020.cfg
hhnk_research_tools/waterschadeschatter/resources/cfg_lizard.cfg
hhnk_research_tools/waterschadeschatter/resources/cfg_lizard_servicedesk.cfg
hhnk_research_tools/waterschadeschatter/resources/cfg_stowa_standaard.cfg
hhnk_research_tools-2024.1.dist-info/METADATA
hhnk_research_tools-2024.1.dist-info/WHEEL
hhnk_research_tools-2024.1.dist-info/top_level.txt
hhnk_research_tools-2024.1.dist-info/RECORD
